<response>
    <href><![CDATA[http://shopname.api.myshoprenter.hu/categories?page=0&limit=25]]></href>
    <page>0</page>
    <limit>25</limit>
    <first>
        <href><![CDATA[http://shopname.api.myshoprenter.hu/categories?page=0&limit=25]]></href>
    </first>
    <previous/>
    <next>
        <href><![CDATA[http://shopname.api.myshoprenter.hu/categories?page=1&limit=25]]></href>
    </next>
    <last>
        <href><![CDATA[http://shopname.api.myshoprenter.hu/categories?page=2&limit=25]]></href>
    </last>
    <items>
        <item>
            <href><![CDATA[http://shopname.api.myshoprenter.hu/categories/Y2F0ZWdvcnktY2F0ZWdvcnlfaWQ9MTg=]]></href>
        </item>
        <item>
            <href><![CDATA[http://shopname.api.myshoprenter.hu/categories/Y2F0ZWdvcnktY2F0ZWdvcnlfaWQ9MjA=]]></href>
        </item>
        <item>
            <href><![CDATA[http://shopname.api.myshoprenter.hu/categories/Y2F0ZWdvcnktY2F0ZWdvcnlfaWQ9MjQ=]]></href>
        </item>
        <item>
            <href><![CDATA[http://shopname.api.myshoprenter.hu/categories/Y2F0ZWdvcnktY2F0ZWdvcnlfaWQ9MjU=]]></href>
        </item>
        <item>
            <href><![CDATA[http://shopname.api.myshoprenter.hu/categories/Y2F0ZWdvcnktY2F0ZWdvcnlfaWQ9MjY=]]></href>
        </item>
        <item>
            <href><![CDATA[http://shopname.api.myshoprenter.hu/categories/Y2F0ZWdvcnktY2F0ZWdvcnlfaWQ9Mjc=]]></href>
        </item>
        <item>
            <href><![CDATA[http://shopname.api.myshoprenter.hu/categories/Y2F0ZWdvcnktY2F0ZWdvcnlfaWQ9Mjg=]]></href>
        </item>
        <item>
            <href><![CDATA[http://shopname.api.myshoprenter.hu/categories/Y2F0ZWdvcnktY2F0ZWdvcnlfaWQ9Mjk=]]></href>
        </item>
        <item>
            <href><![CDATA[http://shopname.api.myshoprenter.hu/categories/Y2F0ZWdvcnktY2F0ZWdvcnlfaWQ9MzA=]]></href>
        </item>
        <item>
            <href><![CDATA[http://shopname.api.myshoprenter.hu/categories/Y2F0ZWdvcnktY2F0ZWdvcnlfaWQ9MzM=]]></href>
        </item>
        <item>
            <href><![CDATA[http://shopname.api.myshoprenter.hu/categories/Y2F0ZWdvcnktY2F0ZWdvcnlfaWQ9MzU=]]></href>
        </item>
        <item>
            <href><![CDATA[http://shopname.api.myshoprenter.hu/categories/Y2F0ZWdvcnktY2F0ZWdvcnlfaWQ9MzY=]]></href>
        </item>
        <item>
            <href><![CDATA[http://shopname.api.myshoprenter.hu/categories/Y2F0ZWdvcnktY2F0ZWdvcnlfaWQ9Mzc=]]></href>
        </item>
        <item>
            <href><![CDATA[http://shopname.api.myshoprenter.hu/categories/Y2F0ZWdvcnktY2F0ZWdvcnlfaWQ9Mzg=]]></href>
        </item>
        <item>
            <href><![CDATA[http://shopname.api.myshoprenter.hu/categories/Y2F0ZWdvcnktY2F0ZWdvcnlfaWQ9Mzk=]]></href>
        </item>
        <item>
            <href><![CDATA[http://shopname.api.myshoprenter.hu/categories/Y2F0ZWdvcnktY2F0ZWdvcnlfaWQ9NDA=]]></href>
        </item>
        <item>
            <href><![CDATA[http://shopname.api.myshoprenter.hu/categories/Y2F0ZWdvcnktY2F0ZWdvcnlfaWQ9NDE=]]></href>
        </item>
        <item>
            <href><![CDATA[http://shopname.api.myshoprenter.hu/categories/Y2F0ZWdvcnktY2F0ZWdvcnlfaWQ9NDI=]]></href>
        </item>
        <item>
            <href><![CDATA[http://shopname.api.myshoprenter.hu/categories/Y2F0ZWdvcnktY2F0ZWdvcnlfaWQ9NDM=]]></href>
        </item>
        <item>
            <href><![CDATA[http://shopname.api.myshoprenter.hu/categories/Y2F0ZWdvcnktY2F0ZWdvcnlfaWQ9NDQ=]]></href>
        </item>
        <item>
            <href><![CDATA[http://shopname.api.myshoprenter.hu/categories/Y2F0ZWdvcnktY2F0ZWdvcnlfaWQ9NDU=]]></href>
        </item>
        <item>
            <href><![CDATA[http://shopname.api.myshoprenter.hu/categories/Y2F0ZWdvcnktY2F0ZWdvcnlfaWQ9NDY=]]></href>
        </item>
        <item>
            <href><![CDATA[http://shopname.api.myshoprenter.hu/categories/Y2F0ZWdvcnktY2F0ZWdvcnlfaWQ9NDc=]]></href>
        </item>
        <item>
            <href><![CDATA[http://shopname.api.myshoprenter.hu/categories/Y2F0ZWdvcnktY2F0ZWdvcnlfaWQ9NDg=]]></href>
        </item>
        <item>
            <href><![CDATA[http://shopname.api.myshoprenter.hu/categories/Y2F0ZWdvcnktY2F0ZWdvcnlfaWQ9NDk=]]></href>
        </item>
    </items>
</response>
